pyrule34/__init__.py
pyrule34/async_rule34.py
pyrule34/objects.py
pyrule34-1.1.0.dist-info/LICENSE
pyrule34-1.1.0.dist-info/METADATA
pyrule34-1.1.0.dist-info/WHEEL
pyrule34-1.1.0.dist-info/top_level.txt
pyrule34-1.1.0.dist-info/RECORD
