Metadata-Version: 2.1
Name: pyrule34
Version: 1.1.0
Summary: Asynchronous wrapper for rule34.xxx.
Home-page: https://github.com/Hypick122/pyrule34
Author: Hypick
Author-email: twerka420@gmail.com
Project-URL: Source, https://github.com/Hypick122/pyrule34
Keywords: async rule34,rule34 api,wrapper
Classifier: Development Status :: 4 - Beta
Classifier: License :: OSI Approved :: GNU General Public License v3 (GPLv3)
Classifier: Operating System :: OS Independent
Classifier: Programming Language :: Python
Classifier: Programming Language :: Python :: 3
Classifier: Programming Language :: Python :: 3.5
Classifier: Programming Language :: Python :: 3.6
Classifier: Programming Language :: Python :: 3.7
Classifier: Programming Language :: Python :: 3.8
Classifier: Programming Language :: Python :: 3.9
Classifier: Programming Language :: Python :: 3.10
Classifier: Programming Language :: Python :: 3.11
Classifier: Programming Language :: Python :: Implementation :: PyPy
Requires-Python: >=3.5
License-File: LICENSE
Requires-Dist: aiohttp (>=3.8.6)
Requires-Dist: beautifulsoup4 (>=4.12.2)
Requires-Dist: lxml (>=4.9.3)
